.coveragerc
HISTORY.rst
LICENSE
MANIFEST.in
README.rst
dev-requirements.txt
requirements.txt
setup.cfg
setup.py
test-requirements.txt
tox.ini
docs/api.rst
docs/conf.py
docs/contributing.rst
docs/index.rst
sprockets/__init__.py
sprockets.clients.cassandra.egg-info/PKG-INFO
sprockets.clients.cassandra.egg-info/SOURCES.txt
sprockets.clients.cassandra.egg-info/dependency_links.txt
sprockets.clients.cassandra.egg-info/namespace_packages.txt
sprockets.clients.cassandra.egg-info/not-zip-safe
sprockets.clients.cassandra.egg-info/requires.txt
sprockets.clients.cassandra.egg-info/top_level.txt
sprockets/clients/__init__.py
sprockets/clients/cassandra/__init__.py