Metadata-Version: 1.1
Name: sprockets.clients.cassandra
Version: 0.1.0
Summary: Base functionality for accessing/modifying data in Cassandra
Home-page: https://github.com/sprockets/sprockets.clients.cassandra.git
Author: AWeber Communications
Author-email: api@aweber.com
License: Copyright (c) 2014 AWeber Communications
